[
  {
    "coordinates": [
      37.636802,
      55.730285
    ],
    "userData": "Москва, Павелецкий вокзал"
  },
  {
    "coordinates": [
      37.633069,
      55.793898
    ],
    "userData": "Москва, Рижский вокзал"
  },
  {
    "coordinates": [
      37.48719,
      55.838558
    ],
    "userData": "м. Водный стадион"
  },
  {
    "coordinates": [
      37.6371587254,
      55.8431447772
    ],
    "userData": "м. Ботанический сад"
  },
  {
    "coordinates": [
      37.4983655238,
      55.8175991765
    ],
    "userData": "м. Войковская"
  },
  {
    "coordinates": [
      37.4610313028,
      55.8098301486
    ],
    "userData": "м. Щукинская"
  },
  {
    "coordinates": [
      37.446804,
      55.730855
    ],
    "userData": "м. Кунцевская"
  },
  {
    "coordinates": [
      37.567633,
      55.743556
    ],
    "userData": "м. Киевская"
  },
  {
    "coordinates": [
      37.515279147774,
      55.7461479133509
    ],
    "userData": "м. Фили"
  },
  {
    "coordinates": [
      37.515491,
      55.736486
    ],
    "userData": "м. Парк Победы"
  },
  {
    "coordinates": [
      37.746397,
      55.788391
    ],
    "userData": "м. Партизанская"
  },
  {
    "coordinates": [
      37.585953,
      55.794251
    ],
    "userData": "м. Савёловская"
  },
  {
    "coordinates": [
      37.7474441193,
      55.7885026019
    ],
    "userData": "м. Партизанская (междугородняя автокасса)"
  },
  {
    "coordinates": [
      37.6389610022,
      55.8458685855
    ],
    "userData": "Москва, м. Ботанический сад"
  },
  {
    "coordinates": [
      37.658618,
      55.776401
    ],
    "userData": "Москва, Ярославский вокзал"
  },
  {
    "coordinates": [
      37.751765,
      55.758308
    ],
    "userData": "м. Шоссе Энтузиастов"
  },
  {
    "coordinates": [
      37.626355693522456,
      55.79231357606657
    ],
    "userData": "Москва, Сущевский Вал, д.64"
  },
  {
    "coordinates": [
      37.660867,
      55.757426
    ],
    "userData": "Москва, Курский вокзал"
  },
  {
    "coordinates": [
      37.560932,
      55.765031
    ],
    "userData": "Москва, м. Улица 1905 года"
  },
  {
    "coordinates": [
      37.473646,
      55.728424
    ],
    "userData": "м. Славянский Бульвар"
  },
  {
    "coordinates": [
      37.56435,
      55.743108
    ],
    "userData": "Москва, Киевский вокзал"
  },
  {
    "coordinates": [
      37.4827877731,
      55.7393608568
    ],
    "userData": "м. Филевский парк"
  },
  {
    "coordinates": [
      37.58195976927681,
      55.7768004905017
    ],
    "userData": "м. Белорусская"
  },
  {
    "coordinates": [
      37.5893374053,
      55.8483931441
    ],
    "userData": "Москва, м.Владыкино"
  },
  {
    "coordinates": [
      37.6807042317,
      55.7469496606
    ],
    "userData": "Москва, м. Площадь Ильича"
  },
  {
    "coordinates": [
      37.6567252185,
      55.7723956034
    ],
    "userData": "Москва, Казанский вокзал"
  },
  {
    "coordinates": [
      37.5176348846,
      55.7363244044
    ],
    "userData": "Москва, м. Парк Победы"
  },
  {
    "coordinates": [
      37.5693871584394,
      55.7416037986967
    ],
    "userData": "Москва, Киевский вокзал (по требованию)"
  },
  {
    "coordinates": [
      37.7447037218,
      55.8048289593
    ],
    "userData": "м. Черкизовская"
  },
  {
    "coordinates": [
      37.5547007739258,
      55.7818327065666
    ],
    "userData": "Больница имени Боткина"
  },
  {
    "coordinates": [
      37.64187,
      55.822867
    ],
    "userData": "м. ВДНХ, северная сторона"
  },
  {
    "coordinates": [
      37.5848978251,
      55.7775078413
    ],
    "userData": "Москва, м. Белорусская, улица Бутырский Вал"
  },
  {
    "coordinates": [
      37.57631,
      55.818046
    ],
    "userData": "м. Тимирязевская"
  },
  {
    "coordinates": [
      37.558017,
      55.793031
    ],
    "userData": "Москва, метро Петровский парк"
  },
  {
    "coordinates": [
      37.7316526220851,
      55.7092458213575
    ],
    "userData": "м. Текстильщики"
  },
  {
    "coordinates": [
      37.5163949588,
      55.7768130661
    ],
    "userData": "м. Полежаевская"
  },
  {
    "coordinates": [
      37.645526,
      55.821736
    ],
    "userData": "Москва, остановка \"Автостанция ВДНХ\""
  },
  {
    "coordinates": [
      37.5724476011876,
      55.8338381038829
    ],
    "userData": "Москва, метро Петровско-Разумовская"
  },
  {
    "coordinates": [
      37.526312,
      55.738575
    ],
    "userData": "Кутузовский проспект, д.36а"
  },
  {
    "coordinates": [
      37.638088734277865,
      55.81907828030325
    ],
    "userData": "м. ВДНХ, южная сторона"
  },
  {
    "coordinates": [
      37.6352290734021,
      55.7317403481233
    ],
    "userData": "Москва, м. Павелецкая"
  },
  {
    "coordinates": [
      37.53442,
      55.740023
    ],
    "userData": "м. Кутузовская"
  },
  {
    "coordinates": [
      37.7507700642895,
      55.8021797610458
    ],
    "userData": "Спорткомплекс \"Измайловский\""
  },
  {
    "coordinates": [
      37.7580656728102,
      55.8038475935839
    ],
    "userData": "ПО \"Сокол\""
  },
  {
    "coordinates": [
      37.7553604916,
      55.7277225429
    ],
    "userData": "Карачаровская эстакада"
  },
  {
    "coordinates": [
      37.6505245199755,
      55.7283622627707
    ],
    "userData": "Новоспасский мост"
  },
  {
    "coordinates": [
      37.4819500185549,
      55.8501291468192
    ],
    "userData": "ул. Флотская"
  },
  {
    "coordinates": [
      37.7483386727955,
      55.7294796199401
    ],
    "userData": "Карачаровский путепровод"
  },
  {
    "coordinates": [
      37.7425880166676,
      55.7318528440625
    ],
    "userData": "Платформа Карачарово"
  },
  {
    "coordinates": [
      37.585173,
      55.77819
    ],
    "userData": "Бутырский вал, д.5"
  },
  {
    "coordinates": [
      37.450901,
      55.723798
    ],
    "userData": "Улица Клочкова"
  },
  {
    "coordinates": [
      37.4491852566,
      55.7263009495
    ],
    "userData": "Станция Кунцево"
  },
  {
    "coordinates": [
      37.578273216102,
      55.7731035599866
    ],
    "userData": "Москва, Грузинский вал (дом 18/15)"
  },
  {
    "coordinates": [
      37.460099,
      55.726013
    ],
    "userData": "Улица Алексея Свиридова"
  },
  {
    "coordinates": [
      37.490707,
      55.73157
    ],
    "userData": "Парк Победы"
  },
  {
    "coordinates": [
      37.4875369497,
      55.7350428484
    ],
    "userData": "Минская улица, 8"
  },
  {
    "coordinates": [
      37.4857378069,
      55.7368949257
    ],
    "userData": "Площадь Ромена Роллана"
  },
  {
    "coordinates": [
      37.4610008828121,
      55.7749688618404
    ],
    "userData": "М. Филевский парк"
  },
  {
    "coordinates": [
      37.454633,
      55.731949
    ],
    "userData": "Кастанаевская, д. 57"
  },
  {
    "coordinates": [
      37.459851,
      55.730393
    ],
    "userData": "Ул.Герасима Курина"
  },
  {
    "coordinates": [
      37.5821570976812,
      55.7087189551715
    ],
    "userData": "Площадь Гагарина"
  },
  {
    "coordinates": [
      37.6113395318,
      55.728776424
    ],
    "userData": "м. Октябрьская, кольцевая"
  },
  {
    "coordinates": [
      37.612112008,
      55.7310528259
    ],
    "userData": "м. Октябрьская, радиальная"
  },
  {
    "coordinates": [
      37.6112537011,
      55.7529376761
    ],
    "userData": "м. Александровский Сад"
  },
  {
    "coordinates": [
      37.6143436059,
      55.7575353661
    ],
    "userData": "м. Охотный Ряд"
  },
  {
    "coordinates": [
      37.6037864311773,
      55.7656167187466
    ],
    "userData": "Пушкинская площадь"
  },
  {
    "coordinates": [
      37.5962333305914,
      55.769487143037
    ],
    "userData": "Триумфальная площадь"
  },
  {
    "coordinates": [
      37.557008706,
      55.7893192793
    ],
    "userData": "м. Динамо"
  },
  {
    "coordinates": [
      37.5323780779,
      55.8003604645
    ],
    "userData": "м. Аэропорт"
  },
  {
    "coordinates": [
      37.5143536333,
      55.8052428563
    ],
    "userData": "м. Сокол"
  },
  {
    "coordinates": [
      37.4813731913,
      55.8393801589
    ],
    "userData": "м. Водный Стадион / Ленинградское шоссе"
  },
  {
    "coordinates": [
      37.6188635839993,
      55.7586864403836
    ],
    "userData": "Театральная площадь"
  },
  {
    "coordinates": [
      37.6281332983547,
      55.7585890936094
    ],
    "userData": "Лубянская площадь"
  },
  {
    "coordinates": [
      37.6340663446951,
      55.7540696344419
    ],
    "userData": "м. Китай-Город"
  },
  {
    "coordinates": [
      37.6044440283352,
      55.7454951328766
    ],
    "userData": "м. Кропоткинская"
  },
  {
    "coordinates": [
      37.6609664788,
      55.8136347527
    ],
    "userData": "Платформа Маленковская"
  },
  {
    "coordinates": [
      37.669636213,
      55.8287210207
    ],
    "userData": "Платформа Яуза"
  },
  {
    "coordinates": [
      37.6692773016,
      55.8442422498
    ],
    "userData": "Платформа Северянин"
  },
  {
    "coordinates": [
      37.505374,
      55.734221
    ],
    "userData": "Поклонная гора"
  },
  {
    "coordinates": [
      37.5297122330825,
      55.7389401701279
    ],
    "userData": "Поклонная улица"
  },
  {
    "coordinates": [
      37.5261717171829,
      55.738056443317
    ],
    "userData": "Панорама \"Бородинская битва\""
  },
  {
    "coordinates": [
      37.665164,
      55.842102
    ],
    "userData": "Станция Ростокино"
  },
  {
    "coordinates": [
      37.4779487372647,
      55.84413720218624
    ],
    "userData": "Пулковская улица"
  },
  {
    "coordinates": [
      37.6574740185239,
      55.8362253215791
    ],
    "userData": "Улица Докукина"
  }
]